README.md
setup.py
XYLLibrary/RequestsKeywords.py
XYLLibrary/XYLKeywords.py
XYLLibrary/__init__.py
XYLLibrary/compat.py
XYLLibrary/demo.py
XYLLibrary/version.py
XYLLibrary.egg-info/PKG-INFO
XYLLibrary.egg-info/SOURCES.txt
XYLLibrary.egg-info/dependency_links.txt
XYLLibrary.egg-info/requires.txt
XYLLibrary.egg-info/top_level.txt