Metadata-Version: 1.0
Name: XYLLibrary
Version: 0.3.0
Summary: python 3.X
Home-page: UNKNOWN
Author: zy
Author-email: 84497503@qq.com
License: MIT License
Keywords: XYLLibrary,robot
Platform: any
